{
  "TARGET_DATABASE": "MDP01_REUSABLE_LAYER",
  "TARGET_TABLE": "CASE_ERLEDIGUNG",
  "CHANGED_RECORDS_TABLE": "temp_v_case_erledigung_changed",
  "INSERT_COLUMNS": [
    "CASE_ERLEDIGUNG_SK",
    "ERLEDIGUNG_ID",
    "GESCHAEFT_ID",
    "GESCHAEFT_SK",
    "ASYL_ERLEDIG_CD",
    "SACHBEARBEITER_UID",
    "EREIGNIS_DAT",
    "STAT_DAT",
    "INAKTIVIERT_JN",
    "INAKTIVIERUNG_DAT",
    "INAKTIVIERUNG_STAT_DAT",
    "INAKTIVIERUNG_BENUTZER"
  ],
  "TABLE_ALIAS": "src",
  "SK_COLUMN": "CASE_ERLEDIGUNG_SK",
  "GUELTIGVON_COL": "VALID_FROM",
  "GUELTIGBIS_COL": "VALID_TO",
  "IST_AKTUELL_COL": "IS_CURRENT",
  "IST_AKTUELL_VAL": "Y",
  "hash_columns": [
    "GESCHAEFT_ID",
    "GESCHAEFT_SK",
    "ASYL_ERLEDIG_CD",
    "SACHBEARBEITER_UID",
    "EREIGNIS_DAT",
    "STAT_DAT",
    "INAKTIVIERT_JN",
    "INAKTIVIERUNG_DAT",
    "INAKTIVIERUNG_STAT_DAT",
    "INAKTIVIERUNG_BENUTZER"
  ],
  "fk_definitions": []
}